Workbook

Sheet Инструкция
A1: Раздел | B1: Как использовать
A2: Назначение | B2: Условные модели к новой книге. Не отчётность реальной компании.
A3: Редактирование | B3: Жёлтые числа — входы; голубые клетки — формулы. Текст поясняет единицы.
A4: Пересчёт | B4: Формулы записаны на английском, как требует XLSX. Откройте в Excel или LibreOffice с автоматическим пересчётом.
A5: Верификация | B5: Формулы базового сценария вычислены независимым ограниченным Python-проверщиком и сохранены в кеше XLSX. openpyxl сам формулы не вычисляет.
A6: При изменении | B6: Контрольные значения относятся только к исходным входам. После изменения сравните новый расчёт отдельно.
A7: Совместимость | B7: Использованы арифметика, SUM, MAX, IF, ROUNDUP; макросов и внешних ссылок нет.
A8: Налоги | B8: Действующие налоговые ставки не включены. Нужен отдельный проверенный справочник по юрисдикции и дате.
A9: Риск | B9: Параметры распределений синтетические, не оценка рисков конкретного хозяйства.
A10: Книга | B10: Нумерация глав в описаниях соответствует книге.
A11: События | B11: Шаблон ГПХ работает с уникальными подтверждёнными событиями. Контроль дублей выполнен в practice.py.
A12: Безопасность | B12: Не помещайте паспорта и реквизиты работников в учебную таблицу.

Sheet Параметры
A1: Параметр | B1: Значение | C1: Единица | D1: Глава / смысл
A2: Цена сырца | B2: 6.5 | C2: сомони/кг | D2: 18,29
A3: Сбор и сбыт | B3: 1.2 | C3: сомони/кг | D3: 18,29
A4: Затраты до уборки | B4: 14000 | C4: сомони/га | D4: 18,29; без повторного включения сбора
A5: Урожайность | B5: 3000 | C5: кг/га | D5: 18,29
A6: Площадь | B6: 50 | C6: га | D6: Модель чувствительности
A7: Инвестиция | B7: 150000 | C7: сомони сегодня | D7: 20
A8: Годовой поток | B8: 60000 | C8: сомони в конце года | D8: 20
A9: Ставка | B9: 0.15 | C9: доля в год | D9: 20
A10: Срок | B10: 5 | C10: лет | D10: 20; расписание фиксировано на пять лет
A11: Начальные деньги | B11: 100000 | C11: сомони | D11: 19
A12: Резерв | B12: 20000 | C12: сомони | D12: 19
A13: Земля | B13: 100 | C13: га | D13: 3
... A18: Готовность | B18: 0.8 | C18: доля | D18: 22

Sheet Маржа
A1: Показатель | B1: Формула / значение | C1: Единица
A2: Выручка на га | B2: ='Параметры'!B2*'Параметры'!B5 -> 19500 | C2: сомони/га
A3: Сбор и сбыт на га | B3: ='Параметры'!B3*'Параметры'!B5 -> 3600 | C3: сомони/га
A4: Маржа после затрат до уборки | B4: =B2-B3-'Параметры'!B4 -> 1900 | C4: сомони/га; не чистая прибыль
A5: Безубыточный урожай | B5: ='Параметры'!B4/('Параметры'!B2-'Параметры'!B3) -> 2641.5094 | C5: кг/га при положительной удельной марже
A6: Безубыточный урожай в ц | B6: =B5/100 -> 26.415094 | C6: ц/га
A7: Общая маржа | B7: =B4*'Параметры'!B6 -> 95000 | C7: сомони
A8: Запас прочности | B8: =('Параметры'!B5-B5)/'Параметры'!B5 -> 0.11949686 | C8: доля

Sheet NPV
A1: Год | B1: Поток | C1: Дисконт-фактор | D1: Приведённый поток | E1: Накопленный PV
A2: 0 | B2: =-'Параметры'!B7 -> -150000 | C2: 1 | D2: =B2*C2 -> -150000 | E2: =D2 -> -150000
A3: 1 | B3: ='Параметры'!B8 -> 60000 | C3: =1/(1+'Параметры'!B9)^A3 -> 0.86956522 | D3: =B3*C3 -> 52173.913 | E3: =E2+D3 -> -97826.087
A4: 2 | B4: ='Параметры'!B8 -> 60000 | C4: =1/(1+'Параметры'!B9)^A4 -> 0.75614367 | D4: =B4*C4 -> 45368.62 | E4: =E3+D4 -> -52457.467
A5: 3 | B5: ='Параметры'!B8 -> 60000 | C5: =1/(1+'Параметры'!B9)^A5 -> 0.65751623 | D5: =B5*C5 -> 39450.974 | E5: =E4+D5 -> -13006.493
A6: 4 | B6: ='Параметры'!B8 -> 60000 | C6: =1/(1+'Параметры'!B9)^A6 -> 0.57175325 | D6: =B6*C6 -> 34305.195 | E6: =E5+D6 -> 21298.702
A7: 5 | B7: ='Параметры'!B8 -> 60000 | C7: =1/(1+'Параметры'!B9)^A7 -> 0.49717674 | D7: =B7*C7 -> 29830.604 | E7: =E6+D7 -> 51129.306
A8: NPV | B8: =SUM(D2:D7) -> 51129.306 | C8: Потоки в конце лет; без остатка
A9: Простая окупаемость | B9: ='Параметры'!B7/'Параметры'!B8 -> 2.5 | C9: лет при равномерном возникновении потока
A10: Ограничение | B10: Срок на листе фиксирован: 5 лет. При другом сроке измените расписание.

Sheet Деньги
A1: Месяц | B1: Поток до финансирования | C1: Остаток без кредита | D1: Потребность до резерва | E1: Пояснение
A2: Начало | B2: 0 | C2: ='Параметры'!B11 -> 100000 | D2: =MAX(0,'Параметры'!B12-C2) -> 0 | E2: Глава 19; проценты не включены
A3: Январь | B3: -80000 | C3: =C2+B3 -> 20000 | D3: =MAX(0,'Параметры'!B12-C3) -> 0
A4: Февраль | B4: -70000 | C4: =C3+B4 -> -50000 | D4: =MAX(0,'Параметры'!B12-C4) -> 70000
A5: Март | B5: 200000 | C5: =C4+B5 -> 150000 | D5: =MAX(0,'Параметры'!B12-C5) -> 0
A6: Пик линии | B6: =MAX(D2:D5) -> 70000 | E6: Потребность, а не дополнительное привлечение каждый месяц

Sheet Рынок
A1: Показатель | B1: Значение | C1: Единица / пояснение
A2: a спроса | B2: 100 | C2: Q=a-bP
A3: b спроса | B3: 2
A4: c предложения | B4: 20 | C4: Q=c+dP
A5: d предложения | B5: 2
A6: Налог | B6: 10 | C6: денег/единицу
A7: Цена без налога | B7: =(B2-B4)/(B3+B5) -> 20
A8: Объём без налога | B8: =B2-B3*B7 -> 60
A9: Цена покупателя с налогом | B9: =(B2-B4+B5*B6)/(B3+B5) -> 25
A10: Цена продавца | B10: =B9-B6 -> 15
A11: Объём с налогом | B11: =B2-B3*B9 -> 50
A12: Доход бюджета | B12: =B6*B11 -> 500
A13: Потеря излишка | B13: =0.5*B6*(B8-B11) -> 50 | C13: Конкуренция; нет внешних эффектов

Sheet Посевной_план
A1: Показатель | B1: Значение | C1: Единица / пояснение
A2: Земля | B2: ='Параметры'!B13 -> 100 | C2: га
A3: Вода | B3: ='Параметры'!B14 -> 300 | C3: условные единицы
A4: Вода хлопок | B4: 5 | C4: на га
A5: Вода пшеница | B5: 2 | C5: на га
A6: Маржа хлопка | B6: 5000 | C6: сомони/га
A7: Маржа пшеницы | B7: 4000 | C7: сомони/га
A8: Хлопок в пересечении | B8: =(B3-B5*B2)/(B4-B5) -> 33.333333 | C8: га; только если оба ограничения активны
A9: Пшеница | B9: =B2-B8 -> 66.666667 | C9: га
A10: Маржа | B10: =B8*B6+B9*B7 -> 433333.33 | C10: сомони
A11: Теневая цена воды | B11: =(B6-B7)/(B4-B5) -> 333.33333 | C11: сомони/единицу, локально
A12: Теневая цена земли | B12: =B7-B5*B11 -> 3333.3333 | C12: сомони/га, локально
A13: Проверка допустимости | B13: =IF(B8<0,"ВНЕ ДИАПАЗОНА",IF(B9<0,"ВНЕ ДИАПАЗОНА","ДОПУСТИМО")) -> ДОПУСТИМО | C13: Если вне диапазона, проверьте граничные планы
A14: Предупреждение | B14: Это формула исходного активного набора, не универсальный LP-решатель.

Sheet Качество
A1: Показатель | B1: Значение | C1: Единица / пояснение
A2: Фактический вес | B2: 10000 | C2: кг нетто
A3: Влажность факт | B3: 0.18 | C3: доля
A4: Влажность стандарт | B4: 0.14 | C4: доля
A5: Сухое вещество | B5: =B2*(1-B3) -> 8200 | C5: кг
A6: Стандартный вес | B6: =B5/(1-B4) -> 9534.8837 | C6: кг; простая модель сохранения сухого вещества
A7: Изменение веса | B7: =B2-B6 -> 465.11628 | C7: кг воды; не автоматическая недостача
A8: Остаток начало | B8: 20 | C8: тонны
A9: Приход | B9: 80 | C9: тонны
A10: Отгрузка | B10: 65 | C10: тонны
A11: Подтверждённые потери | B11: 1 | C11: тонны
A12: Остаток расчёт | B12: =B8+B9-B10-B11 -> 34 | C12: тонны
A13: Остаток инвентаризации | B13: 32 | C13: тонны
A14: Расхождение | B14: =B13-B12 -> -2 | C14: тонны; требует проверки

Sheet Сценарии
A1: Сценарий | B1: Цена, сомони/кг | C1: Урожай, кг/га | D1: Сбор, сомони/кг | E1: До уборки, сомони/га | F1: Маржа, сомони/га
A2: Базовый | B2: 6.5 | C2: 3000 | D2: 1.2 | E2: 14000 | F2: =(B2-D2)*C2-E2 -> 1900
A3: Низкая цена | B3: 6 | C3: 3000 | D3: 1.2 | E3: 14000 | F3: =(B3-D3)*C3-E3 -> 400
A4: Низкий урожай | B4: 6.5 | C4: 2000 | D4: 1.2 | E4: 14000 | F4: =(B4-D4)*C4-E4 -> -3400
A5: Совместный отрицательный | B5: 5.5 | C5: 1800 | D5: 1.2 | E5: 14500 | F5: =(B5-D5)*C5-E5 -> -6760
A6: Положительный | B6: 7 | C6: 3400 | D6: 1.2 | E6: 14000 | F6: =(B6-D6)*C6-E6 -> 5720
A7: Примечание | B7: Сценарии — заданные допущения; вероятности не оценены.

Sheet Техника
A1: Показатель | B1: Значение | C1: Единица / пояснение
A2: Объём уборки | B2: ='Параметры'!B16 -> 4050 | C2: тонны
A3: Мощность | B3: ='Параметры'!B17 -> 1200 | C3: тонны/машину
A4: Готовность | B4: ='Параметры'!B18 -> 0.8 | C4: доля
A5: Расчётная потребность без резерва | B5: =B2/B3 -> 3.375 | C5: нецелое значение мощности
A6: Целые машины исходный сценарий | B6: =ROUNDUP(B5,0) -> 4 | C6: Целое число машин; формула ROUNDUP
A7: CAPEX | B7: =B6*'Параметры'!B15 -> 3300000 | C7: сомони
A8: Эффективная мощность | B8: =B3*B4 -> 960 | C8: тонны/машину
A9: Потребность с готовностью | B9: =B2/B8 -> 4.21875 | C9: нецелое значение мощности
A10: Целые машины с готовностью | B10: =ROUNDUP(B9,0) -> 5 | C10: Целое число машин; формула ROUNDUP
A11: CAPEX с готовностью | B11: =B10*'Параметры'!B15 -> 4125000 | C11: сомони

Sheet ГПХ_шаблон
A1: Event ID | B1: Дата | C1: Исполнитель код | D1: Поле код | E1: Работа код | F1: Объём, га | G1: Тариф, сомони/га | H1: Начисление | I1: Статус
A2: E-001 | B2: 2026-01-15 | C2: P-001 | D2: F-001 | E2: W01 | F2: 2.5 | G2: 100.52 | H2: =F2*G2 -> 251.3 | I2: Учебный акт; подтверждение требуется
A3: E-002 | B3: 2026-02-15 | C3: P-001 | D3: F-001 | E3: W01 | F3: 2.5 | G3: 100.52 | H3: =F3*G3 -> 251.3 | I3: Самостоятельный новый акт, не дубль E-001
A4: Итого | H4: =SUM(H2:H3) -> 502.6
A5: Примечание | B5: В production тариф выбирают по коду и дате; поля защищают правами доступа.
A6: Дубли | B6: Не вставляйте повторные импорты как новые события. Контроль в practice.py.

Sheet Контроль
A1: Модель | B1: Проверено Python | C1: Ссылка на главу | D1: Что проверено
A2: NPV машины | B2: 51129.306 | C2: 20 | D2: 150000; 60000 пять лет;15%
A3: NPV задачи | B3: 14500.376 | C3: 20 | D3: 100000;40000,40000,60000;10%
A4: NPV контрольной работы | B4: 31679.997 | C4: Б, работа 3 | D4: 200000;70000,70000,70000,100000;12%
A5: Кредит с резервом | B5: 70000 | C5: 19 | D5: 100000; -80000,-70000,200000; резерв20000
A6: Вероятность после флага | B6: 0.15384615 | C6: 4 | D6: 1%;90%;5%
A7: Начисления ГПХ | B7: 502.6 | C7: 38 | D7: Два разных события по251,30; дубль исключён
A8: Симуляция: средняя маржа | B8: 974.75984 | C8: 29 | D8: Синтетические треугольные распределения;practice.py
A9: Симуляция: доля отрицательных | B9: 0.38155 | C9: 29 | D9: 20000 реализаций;seed2026
A10: Симуляция:p05 | B10: -3626.7761 | C10: 29 | D10: Учебная модель;не прогноз реального хозяйства
A11: Симуляция:p95 | B11: 5823.9024 | C11: 29 | D11: Учебная модель;не прогноз реального хозяйства
